[
  {
    "type": "ANY",
    "named": true,
    "fields": {},
    "children": {
      "multiple": true,
      "required": false,
      "types": [
        {
          "type": "ASGN",
          "named": true
        },
        {
          "type": "Func",
          "named": true
        },
        {
          "type": "atom",
          "named": true
        },
        {
          "type": "symbol__c_",
          "named": true
        },
        {
          "type": "symbol__cl_",
          "named": true
        },
        {
          "type": "symbol__m",
          "named": true
        },
        {
          "type": "symbol__ml",
          "named": true
        }
      ]
    }
  },
  {
    "type": "ASGN",
    "named": true,
    "fields": {}
  },
  {
    "type": "Derv",
    "named": true,
    "fields": {},
    "children": {
      "multiple": true,
      "required": true,
      "types": [
        {
          "type": "ASGN",
          "named": true
        },
        {
          "type": "Func",
          "named": true
        },
        {
          "type": "Operand",
          "named": true
        },
        {
          "type": "atom",
          "named": true
        },
        {
          "type": "subject",
          "named": true
        },
        {
          "type": "symbol__c_",
          "named": true
        },
        {
          "type": "symbol__cl_",
          "named": true
        },
        {
          "type": "symbol__m",
          "named": true
        },
        {
          "type": "symbol__ml",
          "named": true
        }
      ]
    }
  },
  {
    "type": "EXPORT",
    "named": true,
    "fields": {}
  },
  {
    "type": "EXPR",
    "named": true,
    "fields": {},
    "children": {
      "multiple": true,
      "required": false,
      "types": [
        {
          "type": "ASGN",
          "named": true
        },
        {
          "type": "FuncExpr",
          "named": true
        },
        {
          "type": "atom",
          "named": true
        },
        {
          "type": "subExpr",
          "named": true
        },
        {
          "type": "symbol__c_",
          "named": true
        },
        {
          "type": "symbol__cl_",
          "named": true
        },
        {
          "type": "symbol__m",
          "named": true
        },
        {
          "type": "symbol__ml",
          "named": true
        }
      ]
    }
  },
  {
    "type": "Fork",
    "named": true,
    "fields": {},
    "children": {
      "multiple": true,
      "required": true,
      "types": [
        {
          "type": "Derv",
          "named": true
        },
        {
          "type": "Fork",
          "named": true
        },
        {
          "type": "Operand",
          "named": true
        },
        {
          "type": "nothing",
          "named": true
        }
      ]
    }
  },
  {
    "type": "Func",
    "named": true,
    "fields": {},
    "children": {
      "multiple": true,
      "required": false,
      "types": [
        {
          "type": "FuncExpr",
          "named": true
        },
        {
          "type": "atom",
          "named": true
        },
        {
          "type": "symbol_F",
          "named": true
        },
        {
          "type": "symbol_Fl",
          "named": true
        }
      ]
    }
  },
  {
    "type": "FuncExpr",
    "named": true,
    "fields": {},
    "children": {
      "multiple": true,
      "required": true,
      "types": [
        {
          "type": "ASGN",
          "named": true
        },
        {
          "type": "FuncExpr",
          "named": true
        },
        {
          "type": "Train",
          "named": true
        },
        {
          "type": "symbol_F",
          "named": true
        }
      ]
    }
  },
  {
    "type": "LHS_ANY",
    "named": true,
    "fields": {},
    "children": {
      "multiple": false,
      "required": true,
      "types": [
        {
          "type": "LHS_ELT",
          "named": true
        },
        {
          "type": "LHS_SUB",
          "named": true
        },
        {
          "type": "NAME",
          "named": true
        }
      ]
    }
  },
  {
    "type": "LHS_ATOM",
    "named": true,
    "fields": {},
    "children": {
      "multiple": false,
      "required": true,
      "types": [
        {
          "type": "LHS_ANY",
          "named": true
        },
        {
          "type": "lhsStr",
          "named": true
        }
      ]
    }
  },
  {
    "type": "LHS_ELT",
    "named": true,
    "fields": {},
    "children": {
      "multiple": false,
      "required": true,
      "types": [
        {
          "type": "LHS_ANY",
          "named": true
        },
        {
          "type": "lhsStr",
          "named": true
        }
      ]
    }
  },
  {
    "type": "LHS_ENTRY",
    "named": true,
    "fields": {},
    "children": {
      "multiple": true,
      "required": true,
      "types": [
        {
          "type": "LHS_ELT",
          "named": true
        },
        {
          "type": "NAME",
          "named": true
        },
        {
          "type": "lhs",
          "named": true
        }
      ]
    }
  },
  {
    "type": "LHS_SUB",
    "named": true,
    "fields": {},
    "children": {
      "multiple": false,
      "required": false,
      "types": [
        {
          "type": "symbol_sl",
          "named": true
        }
      ]
    }
  },
  {
    "type": "NAME",
    "named": true,
    "fields": {},
    "children": {
      "multiple": false,
      "required": true,
      "types": [
        {
          "type": "symbol_F",
          "named": true
        },
        {
          "type": "symbol__c_",
          "named": true
        },
        {
          "type": "symbol__m",
          "named": true
        },
        {
          "type": "symbol_s",
          "named": true
        }
      ]
    }
  },
  {
    "type": "Operand",
    "named": true,
    "fields": {},
    "children": {
      "multiple": false,
      "required": true,
      "types": [
        {
          "type": "Derv",
          "named": true
        },
        {
          "type": "subject",
          "named": true
        }
      ]
    }
  },
  {
    "type": "STMT",
    "named": true,
    "fields": {},
    "children": {
      "multiple": false,
      "required": true,
      "types": [
        {
          "type": "EXPORT",
          "named": true
        },
        {
          "type": "EXPR",
          "named": true
        },
        {
          "type": "nothing",
          "named": true
        }
      ]
    }
  },
  {
    "type": "STMT_delimiter",
    "named": true,
    "fields": {}
  },
  {
    "type": "Train",
    "named": true,
    "fields": {},
    "children": {
      "multiple": true,
      "required": true,
      "types": [
        {
          "type": "Derv",
          "named": true
        },
        {
          "type": "Fork",
          "named": true
        }
      ]
    }
  },
  {
    "type": "arg",
    "named": true,
    "fields": {},
    "children": {
      "multiple": true,
      "required": true,
      "types": [
        {
          "type": "Derv",
          "named": true
        },
        {
          "type": "nothing",
          "named": true
        },
        {
          "type": "subExpr",
          "named": true
        },
        {
          "type": "subject",
          "named": true
        }
      ]
    }
  },
  {
    "type": "array",
    "named": true,
    "fields": {},
    "children": {
      "multiple": true,
      "required": false,
      "types": [
        {
          "type": "EXPR",
          "named": true
        },
        {
          "type": "STMT_delimiter",
          "named": true
        }
      ]
    }
  },
  {
    "type": "atom",
    "named": true,
    "fields": {},
    "children": {
      "multiple": true,
      "required": false,
      "types": [
        {
          "type": "array",
          "named": true
        },
        {
          "type": "atom",
          "named": true
        },
        {
          "type": "subExpr",
          "named": true
        },
        {
          "type": "symbol_s",
          "named": true
        },
        {
          "type": "symbol_sl",
          "named": true
        }
      ]
    }
  },
  {
    "type": "lhs",
    "named": true,
    "fields": {},
    "children": {
      "multiple": false,
      "required": true,
      "types": [
        {
          "type": "lhsComp",
          "named": true
        },
        {
          "type": "symbol_s",
          "named": true
        }
      ]
    }
  },
  {
    "type": "lhsComp",
    "named": true,
    "fields": {},
    "children": {
      "multiple": false,
      "required": true,
      "types": [
        {
          "type": "LHS_SUB",
          "named": true
        },
        {
          "type": "lhs",
          "named": true
        },
        {
          "type": "lhsStr",
          "named": true
        }
      ]
    }
  },
  {
    "type": "lhsStr",
    "named": true,
    "fields": {},
    "children": {
      "multiple": true,
      "required": true,
      "types": [
        {
          "type": "LHS_ATOM",
          "named": true
        }
      ]
    }
  },
  {
    "type": "nothing",
    "named": true,
    "fields": {}
  },
  {
    "type": "number",
    "named": true,
    "fields": {}
  },
  {
    "type": "source_file",
    "named": true,
    "fields": {},
    "children": {
      "multiple": true,
      "required": true,
      "types": [
        {
          "type": "STMT",
          "named": true
        },
        {
          "type": "STMT_delimiter",
          "named": true
        }
      ]
    }
  },
  {
    "type": "subExpr",
    "named": true,
    "fields": {},
    "children": {
      "multiple": true,
      "required": true,
      "types": [
        {
          "type": "ASGN",
          "named": true
        },
        {
          "type": "Derv",
          "named": true
        },
        {
          "type": "arg",
          "named": true
        },
        {
          "type": "subExpr",
          "named": true
        }
      ]
    }
  },
  {
    "type": "subject",
    "named": true,
    "fields": {},
    "children": {
      "multiple": true,
      "required": true,
      "types": [
        {
          "type": "ANY",
          "named": true
        },
        {
          "type": "atom",
          "named": true
        }
      ]
    }
  },
  {
    "type": "symbol_Fl",
    "named": true,
    "fields": {}
  },
  {
    "type": "symbol__cl_",
    "named": true,
    "fields": {}
  },
  {
    "type": "symbol__ml",
    "named": true,
    "fields": {}
  },
  {
    "type": "symbol_sl",
    "named": true,
    "fields": {},
    "children": {
      "multiple": false,
      "required": false,
      "types": [
        {
          "type": "number",
          "named": true
        }
      ]
    }
  },
  {
    "type": "!",
    "named": false
  },
  {
    "type": "(",
    "named": false
  },
  {
    "type": ")",
    "named": false
  },
  {
    "type": "+",
    "named": false
  },
  {
    "type": ",",
    "named": false
  },
  {
    "type": "-",
    "named": false
  },
  {
    "type": ".",
    "named": false
  },
  {
    "type": "/",
    "named": false
  },
  {
    "type": "<",
    "named": false
  },
  {
    "type": "=",
    "named": false
  },
  {
    "type": ">",
    "named": false
  },
  {
    "type": "@",
    "named": false
  },
  {
    "type": "TODO:$.LHS_ELT",
    "named": false
  },
  {
    "type": "TODO:$._blMod2_",
    "named": false
  },
  {
    "type": "TODO:$.blSub",
    "named": false
  },
  {
    "type": "TODO:$.hls",
    "named": false
  },
  {
    "type": "TODO:$.lhs",
    "named": false
  },
  {
    "type": "TODO:$.lhsArray",
    "named": false
  },
  {
    "type": "TODO:$.lhsList",
    "named": false
  },
  {
    "type": "TODO:_blMod1",
    "named": false
  },
  {
    "type": "TODO:blFunc",
    "named": false
  },
  {
    "type": "[",
    "named": false
  },
  {
    "type": "]",
    "named": false
  },
  {
    "type": "`",
    "named": false
  },
  {
    "type": "comment",
    "named": true
  },
  {
    "type": "symbol_F",
    "named": true
  },
  {
    "type": "symbol__c_",
    "named": true
  },
  {
    "type": "symbol__m",
    "named": true
  },
  {
    "type": "symbol_s",
    "named": true
  },
  {
    "type": "|",
    "named": false
  },
  {
    "type": "¨",
    "named": false
  },
  {
    "type": "«",
    "named": false
  },
  {
    "type": "¬",
    "named": false
  },
  {
    "type": "¯",
    "named": false
  },
  {
    "type": "´",
    "named": false
  },
  {
    "type": "·",
    "named": false
  },
  {
    "type": "»",
    "named": false
  },
  {
    "type": "×",
    "named": false
  },
  {
    "type": "÷",
    "named": false
  },
  {
    "type": "˘",
    "named": false
  },
  {
    "type": "˙",
    "named": false
  },
  {
    "type": "˜",
    "named": false
  },
  {
    "type": "˝",
    "named": false
  },
  {
    "type": "π",
    "named": false
  },
  {
    "type": "‿",
    "named": false
  },
  {
    "type": "⁼",
    "named": false
  },
  {
    "type": "←",
    "named": false
  },
  {
    "type": "↑",
    "named": false
  },
  {
    "type": "↓",
    "named": false
  },
  {
    "type": "↕",
    "named": false
  },
  {
    "type": "↩",
    "named": false
  },
  {
    "type": "⇐",
    "named": false
  },
  {
    "type": "∊",
    "named": false
  },
  {
    "type": "∘",
    "named": false
  },
  {
    "type": "√",
    "named": false
  },
  {
    "type": "∞",
    "named": false
  },
  {
    "type": "∧",
    "named": false
  },
  {
    "type": "∨",
    "named": false
  },
  {
    "type": "∾",
    "named": false
  },
  {
    "type": "≍",
    "named": false
  },
  {
    "type": "≠",
    "named": false
  },
  {
    "type": "≡",
    "named": false
  },
  {
    "type": "≢",
    "named": false
  },
  {
    "type": "≤",
    "named": false
  },
  {
    "type": "≥",
    "named": false
  },
  {
    "type": "⊏",
    "named": false
  },
  {
    "type": "⊐",
    "named": false
  },
  {
    "type": "⊑",
    "named": false
  },
  {
    "type": "⊒",
    "named": false
  },
  {
    "type": "⊔",
    "named": false
  },
  {
    "type": "⊘",
    "named": false
  },
  {
    "type": "⊢",
    "named": false
  },
  {
    "type": "⊣",
    "named": false
  },
  {
    "type": "⊸",
    "named": false
  },
  {
    "type": "⋄",
    "named": false
  },
  {
    "type": "⋆",
    "named": false
  },
  {
    "type": "⋈",
    "named": false
  },
  {
    "type": "⌈",
    "named": false
  },
  {
    "type": "⌊",
    "named": false
  },
  {
    "type": "⌜",
    "named": false
  },
  {
    "type": "⌽",
    "named": false
  },
  {
    "type": "⌾",
    "named": false
  },
  {
    "type": "⍉",
    "named": false
  },
  {
    "type": "⍋",
    "named": false
  },
  {
    "type": "⍒",
    "named": false
  },
  {
    "type": "⍟",
    "named": false
  },
  {
    "type": "⍷",
    "named": false
  },
  {
    "type": "⎉",
    "named": false
  },
  {
    "type": "⎊",
    "named": false
  },
  {
    "type": "○",
    "named": false
  },
  {
    "type": "◶",
    "named": false
  },
  {
    "type": "⚇",
    "named": false
  },
  {
    "type": "⟜",
    "named": false
  },
  {
    "type": "⟨",
    "named": false
  },
  {
    "type": "⟩",
    "named": false
  },
  {
    "type": "⥊",
    "named": false
  },
  {
    "type": "𝔽",
    "named": false
  },
  {
    "type": "𝔾",
    "named": false
  },
  {
    "type": "𝕊",
    "named": false
  },
  {
    "type": "𝕎",
    "named": false
  },
  {
    "type": "𝕏",
    "named": false
  },
  {
    "type": "𝕗",
    "named": false
  },
  {
    "type": "𝕘",
    "named": false
  },
  {
    "type": "𝕣",
    "named": false
  },
  {
    "type": "𝕤",
    "named": false
  },
  {
    "type": "𝕨",
    "named": false
  },
  {
    "type": "𝕩",
    "named": false
  }
]